Bingus_Tools/__init__.py
Bingus_Tools/tools.py
Bingus_Tools-0.1.2.3.dist-info/METADATA
Bingus_Tools-0.1.2.3.dist-info/WHEEL
Bingus_Tools-0.1.2.3.dist-info/top_level.txt
Bingus_Tools-0.1.2.3.dist-info/RECORD
